sithom/__init__.py
sithom/_version.py
sithom/curve.py
sithom/io.py
sithom/misc.py
sithom/place.py
sithom/plot.py
sithom/time.py
sithom/unc.py
sithom/xr.py
sithom-0.1.1.dist-info/LICENSE
sithom-0.1.1.dist-info/METADATA
sithom-0.1.1.dist-info/WHEEL
sithom-0.1.1.dist-info/top_level.txt
sithom-0.1.1.dist-info/RECORD
